django_rest_passwordreset/__init__.py
django_rest_passwordreset/admin.py
django_rest_passwordreset/apps.py
django_rest_passwordreset/controller.py
django_rest_passwordreset/models.py
django_rest_passwordreset/schema.py
django_rest_passwordreset/signals.py
django_rest_passwordreset/tokens.py
django_rest_passwordreset/urls.py
django_rest_passwordreset/management/__init__.py
django_rest_passwordreset/management/commands/__init__.py
django_rest_passwordreset/management/commands/clearresetpasswodtokens.py
django_rest_passwordreset/migrations/0001_initial.py
django_rest_passwordreset/migrations/0002_pk_migration.py
django_rest_passwordreset/migrations/0003_allow_blank_and_null_fields.py
django_rest_passwordreset/migrations/__init__.py
django_ninja_passwordreset-1.2.4.dist-info/LICENSE
django_ninja_passwordreset-1.2.4.dist-info/WHEEL
django_ninja_passwordreset-1.2.4.dist-info/METADATA
django_ninja_passwordreset-1.2.4.dist-info/RECORD
