Metadata-Version: 2.1
Name: django-ninja-passwordreset
Version: 1.2.4
Summary: An extension of django ninja framework, providing a configurable password reset strategy
Author-email: Christian Kreuzberger <ckreuzberger@anexia-it.com>, Ezeudoh Tochukwu <tochukwu.ezeudoh@gmail.com>
Requires-Python: >=3.7
Classifier: Intended Audience :: Information Technology
Classifier: Intended Audience :: System Administrators
Classifier: Operating System :: OS Independent
Classifier: Topic :: Internet
Classifier: Topic :: Software Development :: Libraries :: Application Frameworks
Classifier: Topic :: Software Development :: Libraries :: Python Modules
Classifier: Topic :: Software Development :: Libraries
Classifier: Topic :: Software Development
Classifier: Typing :: Typed
Classifier: Environment :: Web Environment
Classifier: Intended Audience :: Developers
Classifier: License :: OSI Approved :: MIT License
Classifier: Programming Language :: Python :: 3
Classifier: Programming Language :: Python :: 3.7
Classifier: Programming Language :: Python :: 3.8
Classifier: Programming Language :: Python :: 3.9
Classifier: Programming Language :: Python :: 3.10
Classifier: Programming Language :: Python :: 3.11
Classifier: Programming Language :: Python :: 3 :: Only
Classifier: Framework :: Django
Classifier: Framework :: Django :: 2.1
Classifier: Framework :: Django :: 2.2
Classifier: Framework :: Django :: 3.0
Classifier: Framework :: Django :: 3.1
Classifier: Framework :: Django :: 3.2
Classifier: Framework :: Django :: 4.0
Classifier: Framework :: Django :: 4.1
Classifier: Framework :: AsyncIO
Classifier: Topic :: Internet :: WWW/HTTP :: HTTP Servers
Classifier: Topic :: Internet :: WWW/HTTP
Requires-Dist: Django >=2.1
Requires-Dist: django-ninja-extra
Requires-Dist: pyjwt[crypto]
Requires-Dist: pydantic[email]
Requires-Dist: black==21.12b0 ; extra == "test"
Requires-Dist: isort >=5.0.6,<6.0.0 ; extra == "test"
Requires-Dist: flake8 >=3.8.3,<7.0.0 ; extra == "test"
Requires-Dist: click==8.0.4 ; extra == "test"
Requires-Dist: pytest ; extra == "test"
Requires-Dist: pytest-django ; extra == "test"
Requires-Dist: pytest-cov ; extra == "test"
Project-URL: Documentation, https://github.com/eadwinCode/django-ninja-passwordreset
Project-URL: Source, https://github.com/eadwinCode/django-ninja-passwordreset
Provides-Extra: doc
Provides-Extra: test
